obeenya/__init__.py
obeenya/linear_regression.py
obeenya-0.0.1.dist-info/METADATA
obeenya-0.0.1.dist-info/WHEEL
obeenya-0.0.1.dist-info/top_level.txt
obeenya-0.0.1.dist-info/RECORD
